smart_notes_robot-0.1.0.dist-info/METADATA
smart_notes_robot-0.1.0.dist-info/WHEEL
snr/__init__.py
snr/io.py
snr/vault/__init__.py
snr/vault/classes.py
snr/vault/md.py
smart_notes_robot-0.1.0.dist-info/RECORD
